rigid_body_segmentation/__init__.py
rigid_body_segmentation/__main__.py
rigid_body_segmentation/cli_args.py
rigid_body_segmentation/ndx_file.py
rigid_body_segmentation/rigid_body_segmentation.py
rigid_body_segmentation/test.py
rigid_body_segmentation-0.0.2.dist-info/METADATA
rigid_body_segmentation-0.0.2.dist-info/WHEEL
rigid_body_segmentation-0.0.2.dist-info/top_level.txt
rigid_body_segmentation-0.0.2.dist-info/RECORD
