Metadata-Version: 2.1
Name: rigid_body_segmentation
Version: 0.0.2
Requires-Dist: MDAnalysis>=2.7.0
Requires-Dist: numpy>=1.26.3
Requires-Dist: scikit-learn>=1.4.0
Requires-Dist: rich>=13.7.0
